rsa_835_parser/__init__.py
rsa_835_parser/elements/__init__.py
rsa_835_parser/elements/adjustment_group_code.py
rsa_835_parser/elements/adjustment_reason_code.py
rsa_835_parser/elements/amount_qualifier.py
rsa_835_parser/elements/authorization_information_qualifier.py
rsa_835_parser/elements/claim_status.py
rsa_835_parser/elements/date.py
rsa_835_parser/elements/date_qualifier.py
rsa_835_parser/elements/dollars.py
rsa_835_parser/elements/entity_code.py
rsa_835_parser/elements/entity_type.py
rsa_835_parser/elements/identification_code_qualifier.py
rsa_835_parser/elements/identifier.py
rsa_835_parser/elements/integer.py
rsa_835_parser/elements/organization.py
rsa_835_parser/elements/organization_type.py
rsa_835_parser/elements/payment_method.py
rsa_835_parser/elements/reference_qualifier.py
rsa_835_parser/elements/remark_code.py
rsa_835_parser/elements/remark_qualifier.py
rsa_835_parser/elements/service_code.py
rsa_835_parser/elements/service_modifier.py
rsa_835_parser/elements/service_qualifier.py
rsa_835_parser/elements/utilities.py
rsa_835_parser/loops/__init__.py
rsa_835_parser/loops/claim.py
rsa_835_parser/loops/organization.py
rsa_835_parser/loops/service.py
rsa_835_parser/segments/__init__.py
rsa_835_parser/segments/address.py
rsa_835_parser/segments/amount.py
rsa_835_parser/segments/claim.py
rsa_835_parser/segments/date.py
rsa_835_parser/segments/entity.py
rsa_835_parser/segments/eob_information.py
rsa_835_parser/segments/financial_information.py
rsa_835_parser/segments/interchange.py
rsa_835_parser/segments/location.py
rsa_835_parser/segments/organization.py
rsa_835_parser/segments/reference.py
rsa_835_parser/segments/remark.py
rsa_835_parser/segments/service.py
rsa_835_parser/segments/service_adjustment.py
rsa_835_parser/segments/utilities.py
rsa_835_parser/transaction_set/__init__.py
rsa_835_parser/transaction_set/transaction_set.py
rsa_835_parser/transaction_set/transaction_sets.py
tests/__init__.py
tests/conftest.py
tests/test_edi_835_parser.py
rsa_835_parser-1.42.0.dist-info/LICENSE
rsa_835_parser-1.42.0.dist-info/METADATA
rsa_835_parser-1.42.0.dist-info/WHEEL
rsa_835_parser-1.42.0.dist-info/top_level.txt
rsa_835_parser-1.42.0.dist-info/RECORD
