Metadata-Version: 2.1
Name: rsa-835-parser
Version: 1.42.0
Summary: B Consulting Group EDI 835 file format parser.
Home-page: https://github.com/robsua68/bcg-835-parser
Author: Roberto Suarez
Author-email: <robsua68@hotmail.com>
Keywords: python,EDI,835,X12
Classifier: Development Status :: 3 - Alpha
Requires-Python: >=3.11.5
License-File: LICENSE
Requires-Dist: pandas
